fate_test/__init__.py
fate_test/_ascii.py
fate_test/_client.py
fate_test/_config.py
fate_test/_flow_client.py
fate_test/_io.py
fate_test/_parser.py
fate_test/flow_test/__init__.py
fate_test/flow_test/flow_cli_api.py
fate_test/flow_test/flow_process.py
fate_test/flow_test/flow_rest_api.py
fate_test/flow_test/flow_sdk_api.py
fate_test/scripts/__init__.py
fate_test/scripts/_options.py
fate_test/scripts/_utils.py
fate_test/scripts/benchmark_cli.py
fate_test/scripts/cli.py
fate_test/scripts/config_cli.py
fate_test/scripts/data_cli.py
fate_test/scripts/flow_test_cli.py
fate_test/scripts/generate_mock_data.py
fate_test/scripts/performance_cli.py
fate_test/scripts/testsuite_cli.py
fate_test/utils.py
fate_test-1.6.1.dist-info/entry_points.txt
fate_test-1.6.1.dist-info/WHEEL
fate_test-1.6.1.dist-info/METADATA
fate_test-1.6.1.dist-info/RECORD
