Metadata-Version: 2.1
Name: fate-test
Version: 1.6.1
Summary: test tools for FATE
Home-page: https://fate.fedai.org/
License: Apache-2.0
Keywords: FATE,Federated Learning,Testsuite
Author: FederatedAI
Author-email: contact@FedAI.org
Requires-Python: >=3.6,<4.0
Classifier: Development Status :: 5 - Production/Stable
Classifier: Environment :: Console
Classifier: Intended Audience :: Developers
Classifier: Intended Audience :: Education
Classifier: License :: OSI Approved :: Apache Software License
Classifier: Programming Language :: Python :: 3
Classifier: Programming Language :: Python :: 3.6
Classifier: Programming Language :: Python :: 3.7
Classifier: Programming Language :: Python :: 3.8
Classifier: Programming Language :: Python :: 3.9
Classifier: Topic :: Software Development :: Testing
Requires-Dist: click (>=7.1.2,<8.0.0)
Requires-Dist: colorama (>=0.4.4,<0.5.0)
Requires-Dist: fate_client (==1.6.1)
Requires-Dist: loguru (>=0.5.1,<0.6.0)
Requires-Dist: pandas (>=1.1.5)
Requires-Dist: prettytable (>=1.0.0,<2.0.0)
Requires-Dist: requests (>=2.24.0,<3.0.0)
Requires-Dist: requests_toolbelt (>=0.9.1,<0.10.0)
Requires-Dist: ruamel.yaml (>=0.16.10,<0.17.0)
Requires-Dist: sshtunnel (>=0.1.5,<0.2.0)
Project-URL: Documentation, https://fate.readthedocs.io/en/latest/?badge=latest
Project-URL: Repository, https://github.com/FederatedAI/FATE
